{
  "data": {
    "9bfaf17d2aa6e6c520e6358df8824984": {
      "success": true,
      "data": {
        "videos": [
          {
            "video_id": "dSGvesGrEtM",
            "title": "EMPREGADA GRÁVIDA DESMAIA NA MANSÃO DO MILIONÁRIO E O QUE ESCONDIA NO VENTRE SURPREENDE A TODOS!",
            "description": null,
            "thumbnail": "",
            "duration": "2:04:40",
            "views": 189,
            "likes": 0,
            "published_at": "31 minutes ago",
            "url": "https://youtube.com/watch?v=dSGvesGrEtM"
          },
          {
            "video_id": "GSLCE9f4CKg",
            "title": "\"SUA FILHA PODERIA ANDAR, MAS SUA NOIVA NÃO DEIXA!\"… DESABAFOU O MENINO POBRE AO MILIONÁRIO",
            "description": null,
            "thumbnail": "",
            "duration": "2:04:08",
            "views": 21322,
            "likes": 0,
            "published_at": "1 day ago",
            "url": "https://youtube.com/watch?v=GSLCE9f4CKg"
          },
          {
            "video_id": "D3wVC2ekfaM",
            "title": "MENINO POBRE IMPLORA AO MILIONÁRIO POR LEITE PARA O IRMÃO... E A REAÇÃO DELE TRANSFORMA TUDO",
            "description": null,
            "thumbnail": "",
            "duration": "2:13:40",
            "views": 3280,
            "likes": 0,
            "published_at": "2 days ago",
            "url": "https://youtube.com/watch?v=D3wVC2ekfaM"
          },
          {
            "video_id": "7WjJ-Sd0HSk",
            "title": "MILLIONÁRIO VÊ SEU FILHO AJUDANDO A COZINHEIRA A PREPARAR A COMIDA E PRESENCIA ALGO INESPERADO!",
            "description": null,
            "thumbnail": "",
            "duration": "2:18:44",
            "views": 3744,
            "likes": 0,
            "published_at": "3 days ago",
            "url": "https://youtube.com/watch?v=7WjJ-Sd0HSk"
          },
          {
            "video_id": "exfN4z55B-I",
            "title": "\"PAI, AQUELES DOIS MENINOS DORMINDO NO LIXO SÃO PARECIDOS COMIGO\", DISSE O GAROTO AO MILIONÁRIO!",
            "description": null,
            "thumbnail": "",
            "duration": "2:01:07",
            "views": 148566,
            "likes": 0,
            "published_at": "4 days ago",
            "url": "https://youtube.com/watch?v=exfN4z55B-I"
          },
          {
            "video_id": "u8XYfdgQAcE",
            "title": "MILIONÁRIO COMPRA TODA MERCADORIA DE UMA CRIANÇA VENDENDO DOCES NA RUA E FAZ UM PEDIDO INESPERADO",
            "description": null,
            "thumbnail": "",
            "duration": "2:18:55",
            "views": 3347,
            "likes": 0,
            "published_at": "5 days ago",
            "url": "https://youtube.com/watch?v=u8XYfdgQAcE"
          },
          {
            "video_id": "1zGtqccmwmg",
            "title": "MILIONÁRIO, EM SEUS ÚLTIMOS DIAS, ADOTA DOIS GÊMEOS MENDIGOS… SEM IMAGINAR O IMPACTO EM SUA VIDA",
            "description": null,
            "thumbnail": "",
            "duration": "2:07:17",
            "views": 6701,
            "likes": 0,
            "published_at": "6 days ago",
            "url": "https://youtube.com/watch?v=1zGtqccmwmg"
          },
          {
            "video_id": "jg59niLu7sM",
            "title": "\"ELA É IGUAL A SUA FILHA PERDIDA\", DISSE A NOIVA DO MILIONÁRIO AO VER A GAROTA DESABRIGADA…",
            "description": null,
            "thumbnail": "",
            "duration": "2:20:35",
            "views": 11402,
            "likes": 0,
            "published_at": "7 days ago",
            "url": "https://youtube.com/watch?v=jg59niLu7sM"
          },
          {
            "video_id": "DsoYXKFJIFU",
            "title": "MILIONÁRIO OUVE MENINO POBRE TOCANDO SAXOFONE PARA SALVAR A MÃE… E TOMA UMA AÇÃO QUE CHOCA A TODOS!",
            "description": null,
            "thumbnail": "",
            "duration": "2:18:45",
            "views": 9990,
            "likes": 0,
            "published_at": "8 days ago",
            "url": "https://youtube.com/watch?v=DsoYXKFJIFU"
          },
          {
            "video_id": "0MM6NeraMFo",
            "title": "MILIONÁRIO DISSE À FILHA PARA ESCOLHER UMA NOVA MÃE ENTRE AS RICAS — MAS ELA ESCOLHEU A JARDINEIRA!",
            "description": null,
            "thumbnail": "",
            "duration": "2:07:53",
            "views": 22876,
            "likes": 0,
            "published_at": "9 days ago",
            "url": "https://youtube.com/watch?v=0MM6NeraMFo"
          },
          {
            "video_id": "8lCPtFHpMR0",
            "title": "O FILHO DO MILIONÁRIO NUNCA TINHA ANDADO… ATÉ QUE ELE VIU A BABÁ FAZER ALGO QUE MUDOU TUDO!",
            "description": null,
            "thumbnail": "",
            "duration": "2:23:46",
            "views": 53176,
            "likes": 0,
            "published_at": "10 days ago",
            "url": "https://youtube.com/watch?v=8lCPtFHpMR0"
          },
          {
            "video_id": "H03pcETErZI",
            "title": "O MILIONÁRIO DECIDIU TESTAR SUA EMPREGADA GRÁVIDA E O QUE ENCONTROU NO QUARTO DELA MUDOU TUDO!",
            "description": null,
            "thumbnail": "",
            "duration": "2:07:40",
            "views": 115579,
            "likes": 0,
            "published_at": "11 days ago",
            "url": "https://youtube.com/watch?v=H03pcETErZI"
          },
          {
            "video_id": "lCtTkU4Knr0",
            "title": "NINGUÉM FALAVA COM O MILIONÁRIO… ATÉ QUE A FILHA DA FAXINEIRA ENXUGOU SUAS LÁGRIMAS SEM DIZER NADA!",
            "description": null,
            "thumbnail": "",
            "duration": "2:11:54",
            "views": 121391,
            "likes": 0,
            "published_at": "12 days ago",
            "url": "https://youtube.com/watch?v=lCtTkU4Knr0"
          },
          {
            "video_id": "To-H8V-KGyo",
            "title": "\"POSSO LAVAR SUAS ROUPAS EM TROCA DE COMIDA?\" — O MILIONÁRIO NÃO IMAGINAVA QUE ELA ESTAVA GRÁVIDA!",
            "description": null,
            "thumbnail": "",
            "duration": "2:15:15",
            "views": 9769,
            "likes": 0,
            "published_at": "13 days ago",
            "url": "https://youtube.com/watch?v=To-H8V-KGyo"
          },
          {
            "video_id": "NzUmybtAc1Y",
            "title": "VIÚVA COM DUAS FILHAS RESGATA UM MILIONÁRIO FERIDO À BEIRA DA ESTRADA… E MUDA SUA VIDA PARA SEMPRE!",
            "description": null,
            "thumbnail": "",
            "duration": "2:18:28",
            "views": 75105,
            "likes": 0,
            "published_at": "2 weeks ago",
            "url": "https://youtube.com/watch?v=NzUmybtAc1Y"
          },
          {
            "video_id": "z5m1aIHoF5U",
            "title": "MILIONÁRIO ENTRA NA COZINHA E VÊ A COZINHEIRA AMAMENTANDO SEU BEBÊ… A REAÇÃO DELE CHOCOU TODO MUNDO!",
            "description": null,
            "thumbnail": "",
            "duration": "2:29:55",
            "views": 15912,
            "likes": 0,
            "published_at": "2 weeks ago",
            "url": "https://youtube.com/watch?v=z5m1aIHoF5U"
          },
          {
            "video_id": "6twYZm0q7ag",
            "title": "UM MILIONÁRIO ENCONTROU UM GAROTO CATADOR COM UM BEBÊ NO COLO E TOMOU UMA DECISÃO QUE MUDOU TUDO...",
            "description": null,
            "thumbnail": "",
            "duration": "2:18:11",
            "views": 82202,
            "likes": 0,
            "published_at": "2 weeks ago",
            "url": "https://youtube.com/watch?v=6twYZm0q7ag"
          },
          {
            "video_id": "342Fmwa7c0s",
            "title": "\"VOCÊ NUNCA VAI CONSERTAR ISSO\" – ZOMBARAM DA MENINA DE 12 ANOS, MAS O MILIONÁRIO VIU O MOTOR RUGIR",
            "description": null,
            "thumbnail": "",
            "duration": "2:07:46",
            "views": 4932,
            "likes": 0,
            "published_at": "2 weeks ago",
            "url": "https://youtube.com/watch?v=342Fmwa7c0s"
          },
          {
            "video_id": "joTIJ_9ylZI",
            "title": "MILIONÁRIO VIÚVO CONTRATA UMA EMPREGADA PARA CUIDAR DA FILHA, MAS O QUE ELA FEZ MUDOU TUDO…",
            "description": null,
            "thumbnail": "",
            "duration": "2:17:14",
            "views": 17091,
            "likes": 0,
            "published_at": "2 weeks ago",
            "url": "https://youtube.com/watch?v=joTIJ_9ylZI"
          },
          {
            "video_id": "YdSjmkecNqM",
            "title": "\"NOSSA MÃE FOI EMBORA HOJE…\", DISSE O MENINO. O MILIONÁRIO RESPONDEU: \"VOCÊS AGORA TÊM UM LAR\"",
            "description": null,
            "thumbnail": "",
            "duration": "2:23:03",
            "views": 7304,
            "likes": 0,
            "published_at": "2 weeks ago",
            "url": "https://youtube.com/watch?v=YdSjmkecNqM"
          },
          {
            "video_id": "Vwssh1Fp-4g",
            "title": "GRÁVIDA, SEM TER PRA ONDE IR, ELA DORME SOB UMA ÁRVORE… ATÉ QUE UM MILIONÁRIO APARECE E MUDA TUDO",
            "description": null,
            "thumbnail": "",
            "duration": "2:20:56",
            "views": 85988,
            "likes": 0,
            "published_at": "3 weeks ago",
            "url": "https://youtube.com/watch?v=Vwssh1Fp-4g"
          },
          {
            "video_id": "6FDSo4oG5IU",
            "title": "“TE DOU 2 MILHÕES SE ME CURAR!”, IMPLOROU O MILIONÁRIO… E O TOQUE DO MENINO FEZ O INCRÍVEL ACONTECER",
            "description": null,
            "thumbnail": "",
            "duration": "2:29:05",
            "views": 92966,
            "likes": 0,
            "published_at": "3 weeks ago",
            "url": "https://youtube.com/watch?v=6FDSo4oG5IU"
          },
          {
            "video_id": "z5tYjrTIuB4",
            "title": "MILIONÁRIO VIÚVO VÊ SUA FILHA COM UMA MENINA VENDEDORA DE BALAS… O QUE PRESENCIA MUDA SUA VIDA",
            "description": null,
            "thumbnail": "",
            "duration": "2:43:42",
            "views": 38545,
            "likes": 0,
            "published_at": "3 weeks ago",
            "url": "https://youtube.com/watch?v=z5tYjrTIuB4"
          },
          {
            "video_id": "vlEsLq4U370",
            "title": "OS BEBÊS DO MILIONÁRIO CHORAVAM SEM PARAR… MAS BASTOU UM GESTO DELA E ELES DORMIRAM COMO ANJOS!",
            "description": null,
            "thumbnail": "",
            "duration": "2:18:43",
            "views": 62201,
            "likes": 0,
            "published_at": "3 weeks ago",
            "url": "https://youtube.com/watch?v=vlEsLq4U370"
          },
          {
            "video_id": "pYzbXozTnN8",
            "title": "GAROTINHA CEGA PEDE AJUDA CANTANDO NAS RUAS... MAS A REAÇÃO DO MILIONÁRIO SURPREENDE A TODOS",
            "description": null,
            "thumbnail": "",
            "duration": "2:15:10",
            "views": 9506,
            "likes": 0,
            "published_at": "3 weeks ago",
            "url": "https://youtube.com/watch?v=pYzbXozTnN8"
          },
          {
            "video_id": "lc2WmCiSVe4",
            "title": "PAIS ABANDONAM FILHO ADOTIVO NA MUDANÇA. DIAS DEPOIS, UM MILIONÁRIO COMPRA A CASA...",
            "description": null,
            "thumbnail": "",
            "duration": "2:17:42",
            "views": 10051,
            "likes": 0,
            "published_at": "3 weeks ago",
            "url": "https://youtube.com/watch?v=lc2WmCiSVe4"
          },
          {
            "video_id": "_ZyYDe93KWs",
            "title": "MENINA POBRE DEVOLVE A CARTEIRA DE UM MILIONÁRIO, MAS O QUE VÊ EM SUA MÃO A FAZ CONGELAR...",
            "description": null,
            "thumbnail": "",
            "duration": "2:11:39",
            "views": 49301,
            "likes": 0,
            "published_at": "3 weeks ago",
            "url": "https://youtube.com/watch?v=_ZyYDe93KWs"
          },
          {
            "video_id": "9X681wJ6SuY",
            "title": "MILIONÁRIO É CONVIDADO PARA SER O PAI DE DOIS GÊMEOS NA FESTA DO DIA DOS PAIS E SURPREENDE A TODOS",
            "description": null,
            "thumbnail": "",
            "duration": "2:20:58",
            "views": 3057,
            "likes": 0,
            "published_at": "4 weeks ago",
            "url": "https://youtube.com/watch?v=9X681wJ6SuY"
          },
          {
            "video_id": "Uqj9mKAKC_0",
            "title": "\"SE VOCÊ TRADUZIR, TE DOU TODO MEU DINHEIRO\" — DISSE O MILIONÁRIO, MAS A FAXINEIRA O CALOU NA HORA",
            "description": null,
            "thumbnail": "",
            "duration": "2:15:56",
            "views": 3545,
            "likes": 0,
            "published_at": "4 weeks ago",
            "url": "https://youtube.com/watch?v=Uqj9mKAKC_0"
          },
          {
            "video_id": "8urMRX6OSVw",
            "title": "MÃE SOLTEIRA PERDE O EMPREGO POR AJUDAR UMA MENINA — MAS O MILIONÁRIO PAI DELA MUDA SUA VIDA",
            "description": null,
            "thumbnail": "",
            "duration": "2:18:57",
            "views": 21694,
            "likes": 0,
            "published_at": "4 weeks ago",
            "url": "https://youtube.com/watch?v=8urMRX6OSVw"
          }
        ],
        "total_videos": 30,
        "total_count": 30,
        "message": "✅ 30 títulos extraídos com sucesso!"
      }
    },
    "814e479ee09d71846f6cddf52e51b60b": {
      "success": true,
      "data": {
        "title": "Contos Falados",
        "description": "No Contos Falados, cada história é contada com alma e vai direto ao coração — relatos reais e tocantes que inspiram, emocionam e fazem refletir sobre o que realmente importa. Se você acredita no poder de uma boa narrativa, inscreva-se e deixe que cada conto fale com você.\n",
        "subscriber_count": "48.6K subscribers",
        "video_count": "53 videos"
      }
    },
    "130fe8da25ed250807c9fd2ca4f7b3da": {
      "success": true,
      "data": {
        "channel_id": "UCQ_ixneyao7AfJu79PHwcTA",
        "channel_name": "eusouodh"
      }
    }
  },
  "timestamps": {
    "9bfaf17d2aa6e6c520e6358df8824984": 1755563793.8210506,
    "814e479ee09d71846f6cddf52e51b60b": 1755563798.6204069,
    "130fe8da25ed250807c9fd2ca4f7b3da": 1755565688.7465158
  },
  "saved_at": 1755565688.747772
}